inflate64/__init__.py
inflate64/_inflate64.pypy39-pp73-aarch64-linux-gnu.so
inflate64/py.typed
inflate64-1.0.1.dist-info/top_level.txt
inflate64-1.0.1.dist-info/RECORD
inflate64-1.0.1.dist-info/METADATA
inflate64-1.0.1.dist-info/COPYING
inflate64-1.0.1.dist-info/WHEEL
