Metadata-Version: 2.1
Name: inflate64
Version: 1.0.1
Summary: deflate64 compression/decompression library
Author-email: Hiroshi Miura <miurahr@linux.com>
License: LGPL-2.1-or-later
Keywords: deflate64,compression
Classifier: Development Status :: 5 - Production/Stable
Classifier: License :: OSI Approved :: GNU Lesser General Public License v2 or later (LGPLv2+)
Classifier: Operating System :: MacOS :: MacOS X
Classifier: Operating System :: Microsoft :: Windows
Classifier: Operating System :: POSIX
Classifier: Operating System :: POSIX :: Linux
Classifier: Programming Language :: Python
Classifier: Programming Language :: Python :: 3
Classifier: Programming Language :: Python :: 3.9
Classifier: Programming Language :: Python :: 3.10
Classifier: Programming Language :: Python :: 3.11
Classifier: Programming Language :: Python :: 3.12
Classifier: Programming Language :: Python :: 3.13
Classifier: Programming Language :: Python :: 3 :: Only
Classifier: Programming Language :: Python :: Implementation :: CPython
Classifier: Programming Language :: Python :: Implementation :: PyPy
Classifier: Topic :: Software Development :: Libraries :: Python Modules
Requires-Python: >=3.9
License-File: COPYING
Provides-Extra: test
Requires-Dist: pytest; extra == "test"
Provides-Extra: docs
Requires-Dist: sphinx>=5.0; extra == "docs"
Requires-Dist: docutils; extra == "docs"
Provides-Extra: check
Requires-Dist: mypy>=1.10.0; extra == "check"
Requires-Dist: mypy_extensions>=0.4.1; extra == "check"
Requires-Dist: check-manifest; extra == "check"
Requires-Dist: flake8; extra == "check"
Requires-Dist: flake8-black; extra == "check"
Requires-Dist: flake8-deprecated; extra == "check"
Requires-Dist: flake8-isort; extra == "check"
Requires-Dist: pygments; extra == "check"
Requires-Dist: readme-renderer; extra == "check"
Requires-Dist: twine; extra == "check"
